src/infra/fifo_buffer.v
/*
 * fifo_buffer.v
 *
 * Single-clock AXI-Stream FIFO buffer for audio samples.
 *
 * Notes:
 * - This is a synchronous FIFO, not a clock-domain-crossing FIFO.
 * - Uses active-low asynchronous reset as implemented below.
 * - DEPTH parameter MUST be a power of 2 for pointer wrap to work as written
 * 
 * Key AXI-Stream compliance checklist:
 * - tclk, rst_n, tvalid, tready present on both ends                   YES
 * - tvalid not de-asserted until handshake                             YES
 * - tdata must not change until handshake                              YES
 * - data latched on posedge of clock                                   YES
 * - Handshake occurs when tready && tvalid                             YES
 * 
 * Things to check over
 * - Is it possible for read ptr to pass write ptr (shouldn't be)
 * - Verify combinational logic working on reset
 */

module fifo_buffer #(
    parameter integer WIDTH = 24,
    parameter integer DEPTH = 16
)(
    input  wire                 tclk,
    input  wire                 rst_n,

    input  wire [WIDTH-1:0]     i_tdata,
    input  wire                 i_tvalid,
    output wire                 i_tready,

    output wire [WIDTH-1:0]     o_tdata,
    output wire                 o_tvalid,
    input  wire                 o_tready
);

    localparam integer PTR_WIDTH = $clog2(DEPTH);

    reg [WIDTH-1:0]      fifo_mem         [0:DEPTH-1];
    reg [PTR_WIDTH-1:0]  wr_ptr, rd_ptr;
    reg [PTR_WIDTH:0]    fill_count;
    reg [WIDTH-1:0]      o_tdata_reg;
    reg                  o_tvalid_reg;

    wire full  = (fill_count == DEPTH);
    wire empty = (fill_count == 0);

    // for testing purposes
    wire [WIDTH-1:0] fifo_mem0 = fifo_mem[0];
    wire [WIDTH-1:0] fifo_mem1 = fifo_mem[1];
    wire [WIDTH-1:0] fifo_mem2 = fifo_mem[2];
    wire [WIDTH-1:0] fifo_mem3 = fifo_mem[3];

    wire write_en = i_tvalid && i_tready;
    wire read_en  = o_tvalid && o_tready && !empty;

    assign i_tready = !full;
    assign o_tdata  = o_tdata_reg;
    assign o_tvalid = o_tvalid_reg;

    always @(posedge tclk or negedge rst_n) begin

        // reset mode
        if (!rst_n) begin
            wr_ptr     <= {PTR_WIDTH{1'b0}};
            rd_ptr     <= {PTR_WIDTH{1'b0}};
            fill_count <= {(PTR_WIDTH+1){1'b0}};
            o_tvalid_reg <= 1'b0;
            o_tdata_reg <= {WIDTH{1'b0}};

        // normal operation
        end else begin

            // input
            if (write_en) begin
                // reads old data
                fifo_mem[wr_ptr] <= i_tdata;
                wr_ptr <= wr_ptr + 1'b1;
            end

            // output
            if (read_en) begin
                o_tdata_reg <= fifo_mem[rd_ptr];
                rd_ptr <= rd_ptr + 1'b1;
            end

            // update fill count and tvalid based on what happened
            // YES THIS IS FUCKING AXI-STREAM COMPLIANT BECAUSE HANDSHAKE IS IMPLIED THRU COMBINATIONAL LOGIC
            case ({(write_en), read_en})
                // write, no read
                2'b10: begin
                    fill_count <= fill_count + 1'b1;
                    o_tvalid_reg <= 1'b1;
                end
                // read, no write
                2'b01: begin
                    fill_count <= fill_count - 1'b1;
                    if (fill_count == 1) o_tvalid_reg <= 1'b0; // "empty" wire is a cycle behind so i must use this
                end
                // AND/NAND
                default: fill_count <= fill_count;
            endcase
        end
    end

endmodule

sim/fifo_buffer/fifo_buffer_tb.v
/* TESTS TO ADD LATER

 * - data wraparound in fifo preserves correct element order (ptr and data behaviour)

 * - write when full is ignored (data not stored, pointer doesn't advance)
 * - read when empty is ignored (no data output, pointer doesn't advance)

 * - verify internal reset behaviour
 * - tvalid assertion/de-assertion
 * - AXI-Stream compliance rules (ALL)

 * - interleaved read/write in odd sequence
 * - varying read/write burst lengths
 * - extended read/write cycling
 * - empty->full verify every slot
 * - full->empty verify every slot

 * - do something to protect against no-power of 2 depths (throw error or some shit idfk

Edge Cases

Single-slot FIFO (DEPTH=1)
Power-of-2 boundaries (DEPTH=2, 4, 8, 16)
Maximum fill (all slots written, one read, all written again)
Simultaneous write and read from full FIFO
Simultaneous write and read from single-item FIFO
 */

`timescale 1ns / 1ps
`include "fifo_buffer.v"

module fifo_buffer_tb;

    // Parameters matching DUT
    localparam integer WIDTH = 24;
    localparam integer DEPTH = 8;

    // Clock and reset
    reg tclk;
    reg rst_n;

    // Test data for FIFO
    reg [WIDTH-1:0] test_mem [0:DEPTH-1];

    // DUT input signals
    reg [WIDTH-1:0] i_tdata;
    reg i_tvalid;
    wire i_tready;

    // DUT output signals
    wire [WIDTH-1:0] o_tdata;
    wire o_tvalid;
    reg o_tready;

    // Test control
    integer num_pass = 0;
    integer num_fail = 0;

    // DELAYED RECEIVE test control
    integer correct_responses = 0;
    integer total_responses = 4;

    // TREADY CHECK control
    reg tready_deassert_complete = 0;
    reg tready_assert_complete = 0;

    // Instantiate DUT
    fifo_buffer #(
        .WIDTH(WIDTH),
        .DEPTH(DEPTH)
    ) dut (
        .tclk(tclk),
        .rst_n(rst_n),
        .i_tdata(i_tdata),
        .i_tvalid(i_tvalid),
        .i_tready(i_tready),
        .o_tdata(o_tdata),
        .o_tvalid(o_tvalid),
        .o_tready(o_tready)
    );

    // Clock generation: 10ns period
    initial begin
        tclk = 1'b0;
        forever #5 tclk = ~tclk;
    end

    initial begin

        // Waveform dump
        $dumpfile("fifo_buffer_tb.vcd");
        $dumpvars(0, fifo_buffer_tb);

        // Fill some test data
        test_mem[0] = {(WIDTH/4){4'hA}};
        test_mem[1] = {(WIDTH/4){4'hB}};
        test_mem[2] = {(WIDTH/4){4'hC}};
        test_mem[3] = {(WIDTH/4){4'hD}};

        reset;

        empty_read;

        reset;

        delayed_receive;

        reset;

        tready_check;

        reset;
    end

    // Timeout & summary
    initial begin
        #50000;  // 50µs max simulation time
        $display("\n========== Test Summary ==========");
        $display("Passed: %d", num_pass);
        $display("Failed: %d", num_fail);
        $display("==================================");
        $finish;
    end

    // Reset sequence
    task reset;
        begin
            rst_n = 1'b0;
            i_tdata = {WIDTH{1'b0}};
            i_tvalid = 1'b0;
            o_tready = 1'b0;
            #50;  // Hold reset for 5 clock cycles
            rst_n = 1'b1;
        end
    endtask

    /* =======================================
     *           DELAYED RECEIVE
     * Sends a burst of data
     * Waits
     * Accepts said burst of data
     * Compares against expected output
     * ======================================*/
    task delayed_receive;
        begin
            // open up input line
            i_tvalid = 1'b1;
            @(posedge tclk);

            // send input data
            for(integer i = 0; i < 4; i = i + 1) begin
                i_tdata = test_mem[i];
                if (i == 3) i_tvalid = 1'b0;
                @(posedge tclk);
            end

            // delay
            #100;

            // open up output line; delay to match pipeline output
            o_tready = 1'b1;
            @(posedge tclk);
            @(posedge tclk);
            @(posedge tclk);

            // check outcoming data
            for(integer i = 0; i < 4; i = i + 1) begin
                if (o_tdata == test_mem[i]) begin
                    correct_responses = correct_responses + 1;
                end else $display("expected data: %h | received data: %h", test_mem[i], o_tdata);
                @(posedge tclk);
            end

            // print pass/fail
            if (correct_responses == total_responses) begin
                $display("DELAYED RECEIVE - [PASS]");
                num_pass = num_pass + 1;
            end else begin
                $display("DELAYED RECEIVE - [FAIL]");
                num_fail = num_fail + 1;
            end
            
            #100;
        end
    endtask


    /* =======================================
     *             EMPTY READ
     * **Assumes the fifo mem register is empty
     * **Assumes reset just happened
     * Opens up output line
     * Check if data comes out or valid go high
     * ======================================*/
    task empty_read;
        begin
            o_tready = 1'b1;
            if (o_tvalid == 1'b1 || o_tdata != {WIDTH{1'b0}}) begin
                $display("EMPTY READ - [FAIL]");
                num_fail = num_fail + 1;
            end else begin
                $display("EMPTY READ - [PASS]");
                num_pass = num_pass + 1;
            end
        end
    endtask

    /* =======================================
     *              TREADY CHECK
     * Sends more data than depth
     * Checks for de-assertion when full (handshake)
     * Checks for re-assertion when !full (handshake)
     * ======================================*/
    task tready_check;
        begin
            i_tvalid = 1'b1;
            @(posedge tclk);

            // fill memory & check for de-assertion
            for (integer i = 0; i < DEPTH + 4; i = i + 1) begin
                i_tdata = test_mem[ i % 4 ];
                if (i_tready == 1'b0) begin
                    tready_deassert_complete = 1'b1;
                end
                @(posedge tclk);
            end

            // open up output line and check for re-assertion
            o_tready = 1'b1;
            @(posedge tclk);
            @(posedge tclk);
            if (i_tready == 1'b1) tready_assert_complete = 1'b1;

            @(posedge tclk);

            if (tready_assert_complete && tready_deassert_complete) begin
                $display("TREADY CHECK - [PASS]");
                num_pass = num_pass + 1;
            end else begin
                $display("TREADY CHECK - [FAIL]");
                num_fail = num_fail + 1;
            end
        end
    endtask

endmodule

sim/fifo_buffer/fifo_buffer_tb.vcd
$date
	Thu Jun 11 21:36:31 2026
$end
$version
	Icarus Verilog
$end
$timescale
	1ps
$end
$scope module fifo_buffer_tb $end
$var wire 1 ! o_tvalid $end
$var wire 24 " o_tdata [23:0] $end
$var wire 1 # i_tready $end
$var parameter 32 $ DEPTH $end
$var parameter 32 % WIDTH $end
$var reg 24 & i_tdata [23:0] $end
$var reg 1 ' i_tvalid $end
$var reg 1 ( o_tready $end
$var reg 1 ) rst_n $end
$var reg 1 * tclk $end
$var reg 1 + tready_assert_complete $end
$var reg 1 , tready_deassert_complete $end
$var integer 32 - correct_responses [31:0] $end
$var integer 32 . num_fail [31:0] $end
$var integer 32 / num_pass [31:0] $end
$var integer 32 0 total_responses [31:0] $end
$scope module dut $end
$var wire 24 1 fifo_mem0 [23:0] $end
$var wire 24 2 fifo_mem1 [23:0] $end
$var wire 24 3 fifo_mem2 [23:0] $end
$var wire 24 4 fifo_mem3 [23:0] $end
$var wire 24 5 i_tdata [23:0] $end
$var wire 1 ' i_tvalid $end
$var wire 24 6 o_tdata [23:0] $end
$var wire 1 ( o_tready $end
$var wire 1 7 read_en $end
$var wire 1 ) rst_n $end
$var wire 1 * tclk $end
$var wire 1 8 write_en $end
$var wire 1 ! o_tvalid $end
$var wire 1 # i_tready $end
$var wire 1 9 full $end
$var wire 1 : empty $end
$var parameter 32 ; DEPTH $end
$var parameter 32 < PTR_WIDTH $end
$var parameter 32 = WIDTH $end
$var reg 4 > fill_count [3:0] $end
$var reg 24 ? o_tdata_reg [23:0] $end
$var reg 1 ! o_tvalid_reg $end
$var reg 3 @ rd_ptr [2:0] $end
$var reg 3 A wr_ptr [2:0] $end
$upscope $end
$scope task delayed_receive $end
$scope begin $ivl_for_loop0 $end
$var integer 32 B i [31:0] $end
$upscope $end
$scope begin $ivl_for_loop1 $end
$var integer 32 C i [31:0] $end
$upscope $end
$upscope $end
$scope task empty_read $end
$upscope $end
$scope task reset $end
$upscope $end
$scope task tready_check $end
$scope begin $ivl_for_loop2 $end
$var integer 32 D i [31:0] $end
$upscope $end
$upscope $end
$upscope $end
$enddefinitions $end
$comment Show the parameter values. $end
$dumpall
b11000 =
b11 <
b1000 ;
b11000 %
b1000 $
$end
#0
$dumpvars
bx D
bx C
bx B
b0 A
b0 @
b0 ?
b0 >
1:
09
08
07
b0 6
b0 5
bx 4
bx 3
bx 2
bx 1
b100 0
b0 /
b0 .
b0 -
0,
0+
0*
0)
0(
0'
b0 &
1#
b0 "
0!
$end
#5000
1*
#10000
0*
#15000
1*
#20000
0*
#25000
1*
#30000
0*
#35000
1*
#40000
0*
#45000
1*
#50000
0*
b1 /
0(
0)
#55000
1*
#60000
0*
#65000
1*
#70000
0*
#75000
1*
#80000
0*
#85000
1*
#90000
0*
#95000
1*
#100000
18
0*
1'
1)
#105000
1!
0:
b1 >
b1 A
b101010101010101010101010 1
b101010101010101010101010 &
b101010101010101010101010 5
b0 B
1*
#110000
0*
#115000
b10 >
b10 A
b101110111011101110111011 2
b101110111011101110111011 &
b101110111011101110111011 5
b1 B
1*
#120000
0*
#125000
b11 >
b11 A
b110011001100110011001100 3
b110011001100110011001100 &
b110011001100110011001100 5
b10 B
1*
#130000
0*
#135000
b100 >
b100 A
b110111011101110111011101 4
08
0'
b110111011101110111011101 &
b110111011101110111011101 5
b11 B
1*
#140000
0*
#145000
b100 B
1*
#150000
0*
#155000
1*
#160000
0*
#165000
1*
#170000
0*
#175000
1*
#180000
0*
#185000
1*
#190000
0*
#195000
1*
#200000
0*
#205000
1*
#210000
0*
#215000
1*
#220000
0*
#225000
1*
#230000
0*
#235000
1*
#240000
0*
#245000
17
1*
1(
#250000
0*
#255000
b11 >
b1 @
b101010101010101010101010 "
b101010101010101010101010 6
b101010101010101010101010 ?
1*
#260000
0*
#265000
b10 >
b10 @
b101110111011101110111011 "
b101110111011101110111011 6
b101110111011101110111011 ?
b1 -
b0 C
1*
#270000
0*
#275000
b1 >
b11 @
b110011001100110011001100 "
b110011001100110011001100 6
b110011001100110011001100 ?
b10 -
b1 C
1*
#280000
0*
#285000
07
0!
1:
b0 >
b100 @
b110111011101110111011101 "
b110111011101110111011101 6
b110111011101110111011101 ?
b11 -
b10 C
1*
#290000
0*
#295000
b100 -
b11 C
1*
#300000
0*
#305000
b10 /
b100 C
1*
#310000
0*
#315000
1*
#320000
0*
#325000
1*
#330000
0*
#335000
1*
#340000
0*
#345000
1*
#350000
0*
#355000
1*
#360000
0*
#365000
1*
#370000
0*
#375000
1*
#380000
0*
#385000
1*
#390000
0*
#395000
1*
#400000
0*
#405000
b0 "
b0 6
b0 ?
b0 @
b0 A
1*
0(
b0 &
b0 5
0)
#410000
0*
#415000
1*
#420000
0*
#425000
1*
#430000
0*
#435000
1*
#440000
0*
#445000
1*
#450000
0*
#455000
1!
0:
b1 >
b1 A
b101010101010101010101010 &
b101010101010101010101010 5
b0 D
18
1*
1'
1)
#460000
0*
#465000
b10 >
b10 A
b101110111011101110111011 &
b101110111011101110111011 5
b1 D
1*
#470000
0*
#475000
b11 >
b11 A
b110011001100110011001100 &
b110011001100110011001100 5
b10 D
1*
#480000
0*
#485000
b100 >
b100 A
b110111011101110111011101 &
b110111011101110111011101 5
b11 D
1*
#490000
0*
#495000
b101 >
b101 A
b101010101010101010101010 &
b101010101010101010101010 5
b100 D
1*
#500000
0*
#505000
b110 >
b110 A
b101110111011101110111011 &
b101110111011101110111011 5
b101 D
1*
#510000
0*
#515000
b111 >
b111 A
b110011001100110011001100 &
b110011001100110011001100 5
b110 D
1*
#520000
0*
#525000
08
0#
19
b1000 >
b0 A
b110111011101110111011101 &
b110111011101110111011101 5
b111 D
1*
#530000
0*
#535000
1,
b101010101010101010101010 &
b101010101010101010101010 5
b1000 D
1*
#540000
0*
#545000
b101110111011101110111011 &
b101110111011101110111011 5
b1001 D
1*
#550000
0*
#555000
b110011001100110011001100 &
b110011001100110011001100 5
b1010 D
1*
#560000
0*
#565000
b110111011101110111011101 &
b110111011101110111011101 5
b1011 D
1*
#570000
0*
#575000
17
1(
b1100 D
1*
#580000
0*
#585000
18
1#
09
b111 >
b1 @
b101010101010101010101010 "
b101010101010101010101010 6
b101010101010101010101010 ?
1*
#590000
0*
#595000
b10 @
b101110111011101110111011 "
b101110111011101110111011 6
b101110111011101110111011 ?
b1 A
b110111011101110111011101 1
1+
1*
#600000
0*
#605000
b0 "
b0 6
b0 ?
0!
1:
b0 >
b0 @
b0 A
07
08
0(
0'
b0 &
b0 5
0)
b11 /
1*
#610000
0*
#615000
1*
#620000
0*
#625000
1*
#630000
0*
#635000
1*
#640000
0*
#645000
1*
#650000
0*
#655000
1*
1)
