src/infra/i2s_in.v
module transceiver_in #(
    parameter WIDTH = 24,
    parameter COUNTER_BITS = 5    // 5 bits covers 0–24
)(
    // general state
    input  wire             rst_n,
    input  wire             clk, // doubles as sck

    // incoming
    input  wire             ws,
    input  wire             sd,

    // outgoing
    input wire              o_tready,
    output reg              o_tvalid,
    output reg  [WIDTH-1:0] tdata
);

reg r_ws, r_sd;
reg r_ws_last;
reg new_word_temp;

reg state; // 0 is idle, 1 is processing word

reg [COUNTER_BITS-1:0] word_counter;

reg [WIDTH-1:0] channel_1;
reg [WIDTH-1:0] channel_2;

always @(posedge clk) begin

    if (!rst_n) begin // reset logic
        o_tvalid     <= 1'b0;
        tdata        <= {WIDTH{1'b0}}; 

        r_sd         <= 1'b0;
        r_ws         <= ws;
        r_ws_last    <= ws;

        word_counter <= 5'b0;
        channel_1    <= 24'b0;
        channel_2    <= 24'b0;
        state        <= 1'b0;
    end 
    
    else begin
        // latch inputs (1 cycle delay) for stability
        r_ws <= ws;
        r_sd <= sd;

        // Handle AXI-S handshake backpressure
        // if (o_tready && o_tvalid) begin
        //     o_tvalid <= 1'b0; 
        // end

        // ── NEW WORD DETECTED (WS EDGE) ─────────
        if (r_ws_last != r_ws) begin
            r_ws_last    <= r_ws;
            word_counter <= 5'b1; // Reset counter, wait for NEXT cycle to sample MSB
            state        <= 1'b1;

            // write first data bit
            if (r_ws)
                channel_2[(WIDTH - 1)] <= r_sd;
            else
                channel_1[(WIDTH - 1)] <= r_sd;
            
            // Handle back-to-back I2S words safely (WS toggling exactly at word end)
            if (word_counter == (WIDTH - 1)) begin
                // o_tvalid <= 1'b1;
                // Reading old value of r_ws_last here correctly grabs the finished channel
                tdata    <= r_ws_last ? channel_2 : channel_1;
            end
        end
        // ── SHIFTING DATA ──
        else if (state != 0) begin // does not get entered
            if (word_counter == WIDTH) begin
                // o_tvalid <= 1'b1;
                $display("WORD END");
                state    <= 1'b0; // back to idle
                tdata    <= r_ws ? channel_2[23:0] : channel_1[23:0]; 
            end else begin // GETS ENABLED
                // Write to bit [WIDTH-1 - word_counter]
                if (r_ws)
                    channel_2[(WIDTH - 1) - word_counter] <= r_sd;
                else
                    channel_1[(WIDTH - 1) - word_counter] <= r_sd;
                
                word_counter <= word_counter + 1;

                // TEMPORARY VALID DE-ASSERTION FIX
                if(word_counter == 5) begin
                    o_tvalid <= 1'b0;
                end
            end
        end
    end
end
endmodule

tb/i2s_in_tb.v
`timescale 1ns / 1ps
`include "i2s_in.v"

// =================================================================
//  Testbench: i2s_in_tb
//  DUT:       transceiver_in
//
//  Drives a synthetic I2S stream on ws/sd and checks that the DUT
//  correctly shifts each 24-bit word into channel_1 / channel_2 and
//  latches the result onto tdata. Internal regs (channel_1,
//  channel_2, word_counter, state) are inspected directly through
//  hierarchical references for diagnostics on failure.
// =================================================================

module i2s_in_tb;

  // ======================= Parameters =======================
  localparam WIDTH        = 24;
  localparam COUNTER_BITS = 5;
  localparam CLK_PERIOD   = 10;   // 10ns period -> clk doubles as sck

  // ======================= DUT signals =======================
  reg                   rst_n;
  reg                   clk;
  reg                   ws;
  reg                   sd;
  reg                   o_tready;
  wire                  o_tvalid;
  wire [WIDTH-1:0]      tdata;

  // ======================= Test control =======================
  integer num_pass, num_fail;
  integer test_num;

  // failure log (name + detail), printed again at the very end
  reg [8*48-1:0] fail_name [0:31];
  reg [8*80-1:0] fail_detail [0:31];
  integer        fail_count;

  // ======================= DUT instantiation =======================
  transceiver_in #(
      .WIDTH        (WIDTH),
      .COUNTER_BITS (COUNTER_BITS)
  ) dut (
      .rst_n    (rst_n),
      .clk      (clk),
      .ws       (ws),
      .sd       (sd),
      .o_tready (o_tready),
      .o_tvalid (o_tvalid),
      .tdata    (tdata)
  );

  // ======================= Clock generation =======================
  initial begin
    clk = 1'b0;
    forever #(CLK_PERIOD/2) clk = ~clk;
  end

  // ======================= Test sequence =======================
  initial begin
    num_pass   = 0;
    num_fail   = 0;
    test_num   = 0;
    fail_count = 0;
    o_tready   = 1'b1;     // o_tready is currently unused by the DUT (backpressure
                            // logic is commented out) - tied high so it never looks
                            // like the cause of any failure below
    ws         = 1'b1;     // held high through the first reset so the first word
    sd         = 1'b0;     // (ws=0) below produces a clean WS edge

    reset;
    test_reset_state;

    reset;
    test_single_word_ch1;
    test_single_word_ch2;

    test_back_to_back_words;

    reset;
    test_tvalid_behavior;

    test_reset_mid_word;

    #200;
    print_summary;
    $finish;
  end

  // =======================================================
  //  reset: synchronous, active-low
  // =======================================================
  task reset;
  begin
    rst_n = 1'b0;
    #(CLK_PERIOD * 3);
    @(posedge clk);
    rst_n = 1'b1;
    @(posedge clk);
  end
  endtask

  // =======================================================
  //  i2s_drive_bits: shift one WIDTH-bit word's worth of data
  //  onto sd, transitioning ws to ws_val on the very first bit.
  //  Does NOT add any idle gap before or after - back-to-back
  //  calls produce a back-to-back (zero-gap) I2S stream.
  // =======================================================
  task i2s_drive_bits;
    input             ws_val;
    input [WIDTH-1:0] data;
    integer bit_i;
    begin
      for (bit_i = 0; bit_i < WIDTH; bit_i = bit_i + 1) begin
        @(negedge clk);
        if (bit_i == 0)
          ws = ws_val;               // WS edge coincides with MSB
        sd = data[WIDTH-1-bit_i];    // MSB first
        @(posedge clk);
      end
    end
  endtask

  // =======================================================
  //  wait_for_tdata: poll tdata for up to timeout_cycles posedges,
  //  setting found=1 the moment tdata matches expected. Always
  //  consumes the full timeout so callers land on a known cycle.
  // =======================================================
  task wait_for_tdata;
    input  [WIDTH-1:0] expected;
    input  integer     timeout_cycles;
    output             found;
    integer k;
    begin
      found = 1'b0;
      for (k = 0; k < timeout_cycles; k = k + 1) begin
        @(posedge clk);
        if (tdata === expected)
          found = 1'b1;
      end
    end
  endtask

  // =======================================================
  //  log_fail / print_summary
  // =======================================================
  task log_fail;
    input [8*48-1:0] name;
    input [8*80-1:0] detail;
    begin
      fail_name[fail_count]   = name;
      fail_detail[fail_count] = detail;
      fail_count = fail_count + 1;
    end
  endtask

  task print_summary;
    integer f;
    begin
      $display("");
      $display("=========================================");
      $display("              TEST SUMMARY                ");
      $display("=========================================");
      $display("  Passed : %0d", num_pass);
      $display("  Failed : %0d", num_fail);
      $display("=========================================");

      if (fail_count > 0) begin
        $display("");
        $display("=========================================");
        $display("            FAILURE SUMMARY               ");
        $display("=========================================");
        for (f = 0; f < fail_count; f = f + 1) begin
          $display("  [%0d] %0s", f+1, fail_name[f]);
          $display("        %0s", fail_detail[f]);
        end
        $display("=========================================");
      end else begin
        $display("  All tests passed - no failures logged.");
      end
    end
  endtask

  // =======================================================
  //  TEST: reset state
  //  All outputs and internal accumulators should sit at 0
  //  immediately after reset.
  // =======================================================
  task test_reset_state;
  begin
    test_num = test_num + 1;
    if (tdata === {WIDTH{1'b0}} && o_tvalid === 1'b0 &&
        dut.channel_1 === {WIDTH{1'b0}} && dut.channel_2 === {WIDTH{1'b0}} &&
        dut.word_counter === {COUNTER_BITS{1'b0}} && dut.state === 1'b0) begin
      $display("[PASS] Test %0d: test_reset_state", test_num);
      num_pass = num_pass + 1;
    end else begin
      $display("[FAIL] Test %0d: test_reset_state", test_num);
      $display("        tdata=%h o_tvalid=%b channel_1=%h channel_2=%h word_counter=%0d state=%b",
                tdata, o_tvalid, dut.channel_1, dut.channel_2, dut.word_counter, dut.state);
      num_fail = num_fail + 1;
      log_fail("test_reset_state", "internal state not fully cleared after reset");
    end
  end
  endtask

  // =======================================================
  //  TEST: single word, channel 1 (ws = 0)
  //  Sends one isolated word with idle settle time before/after
  //  and checks tdata picks it up.
  // =======================================================
  reg [WIDTH-1:0] word_ch1;
  reg             found_ch1;
  task test_single_word_ch1;
  begin
    test_num = test_num + 1;
    word_ch1 = 24'hA5C33C;

    i2s_drive_bits(1'b0, word_ch1);
    wait_for_tdata(word_ch1, 10, found_ch1);

    if (found_ch1) begin
      $display("[PASS] Test %0d: test_single_word_ch1 -- tdata = %h", test_num, tdata);
      num_pass = num_pass + 1;
    end else begin
      $display("[FAIL] Test %0d: test_single_word_ch1 -- expected tdata = %h, got = %h",
                test_num, word_ch1, tdata);
      $display("        channel_1=%h channel_2=%h word_counter=%0d state=%b",
                dut.channel_1, dut.channel_2, dut.word_counter, dut.state);
      num_fail = num_fail + 1;
      log_fail("test_single_word_ch1", "tdata never matched expected channel-1 word");
    end
  end
  endtask

  // =======================================================
  //  TEST: single word, channel 2 (ws = 1)
  //  Run immediately after test_single_word_ch1 (which already
  //  leaves the bus idle), so this also exercises a normal
  //  WS toggle from a settled idle state.
  // =======================================================
  reg [WIDTH-1:0] word_ch2;
  reg             found_ch2;
  task test_single_word_ch2;
  begin
    test_num = test_num + 1;
    word_ch2 = 24'h7E1234;

    i2s_drive_bits(1'b1, word_ch2);
    wait_for_tdata(word_ch2, 10, found_ch2);

    if (found_ch2) begin
      $display("[PASS] Test %0d: test_single_word_ch2 -- tdata = %h", test_num, tdata);
      num_pass = num_pass + 1;
    end else begin
      $display("[FAIL] Test %0d: test_single_word_ch2 -- expected tdata = %h, got = %h",
                test_num, word_ch2, tdata);
      $display("        channel_1=%h channel_2=%h word_counter=%0d state=%b",
                dut.channel_1, dut.channel_2, dut.word_counter, dut.state);
      num_fail = num_fail + 1;
      log_fail("test_single_word_ch2", "tdata never matched expected channel-2 word");
    end
  end
  endtask

  // =======================================================
  //  TEST: back-to-back words, zero idle gap between them
  //  (WS toggles straight from the last bit of word C into the
  //  first bit of word D, per the DUT's "back-to-back" comment).
  //
  //  Sub-check (a): word C's bits should still land correctly
  //                 in channel_1 even though it never gets idle
  //                 time to settle.
  //  Sub-check (b): tdata should eventually present word D.
  // =======================================================
  reg [WIDTH-1:0] word_c, word_d;
  reg             found_d;
  task test_back_to_back_words;
  begin
    word_c = 24'h112233;
    word_d = 24'hFEDCBA;

    i2s_drive_bits(1'b0, word_c);   // channel 1 word, no settle afterwards
    i2s_drive_bits(1'b1, word_d);   // channel 2 word, WS toggles immediately

    // sub-check (a): was word C's data correctly shifted into channel_1?
    test_num = test_num + 1;
    if (dut.channel_1 === word_c) begin
      $display("[PASS] Test %0d: test_back_to_back_words(a) -- channel_1 = %h", test_num, dut.channel_1);
      num_pass = num_pass + 1;
    end else begin
      $display("[FAIL] Test %0d: test_back_to_back_words(a) -- expected channel_1 = %h, got = %h",
                test_num, word_c, dut.channel_1);
      num_fail = num_fail + 1;
      log_fail("test_back_to_back_words(a)", "channel_1 did not capture the pre-toggle word's bits");
    end

    // sub-check (b): does tdata ever present word D?
    wait_for_tdata(word_d, 10, found_d);
    test_num = test_num + 1;
    if (found_d) begin
      $display("[PASS] Test %0d: test_back_to_back_words(b) -- tdata = %h", test_num, tdata);
      num_pass = num_pass + 1;
    end else begin
      $display("[FAIL] Test %0d: test_back_to_back_words(b) -- expected tdata = %h, got = %h",
                test_num, word_d, tdata);
      $display("        channel_1=%h channel_2=%h word_counter=%0d state=%b",
                dut.channel_1, dut.channel_2, dut.word_counter, dut.state);
      num_fail = num_fail + 1;
      log_fail("test_back_to_back_words(b)", "tdata never latched the word following a zero-gap WS toggle");
    end
  end
  endtask

  // =======================================================
  //  TEST: o_tvalid behavior
  //  In the source as given, every "o_tvalid <= 1'b1" assertion
  //  is commented out - the only live assignment to o_tvalid
  //  outside reset is the de-assertion at word_counter == 5.
  //  This test documents that o_tvalid never goes high while
  //  words are streamed, matching the DUT as written.
  // =======================================================
  reg [WIDTH-1:0] word_tv;
  reg             tvalid_seen_high;
  integer         tv_i;
  task test_tvalid_behavior;
  begin
    test_num = test_num + 1;
    word_tv = 24'h00FF00;
    tvalid_seen_high = 1'b0;

    for (tv_i = 0; tv_i < WIDTH; tv_i = tv_i + 1) begin
      @(negedge clk);
      if (tv_i == 0) ws = 1'b0;
      sd = word_tv[WIDTH-1-tv_i];
      @(posedge clk);
      if (o_tvalid === 1'b1)
        tvalid_seen_high = 1'b1;
    end

    if (!tvalid_seen_high) begin
      $display("[PASS] Test %0d: test_tvalid_behavior -- o_tvalid stayed low (matches commented-out assert lines in DUT)", test_num);
      num_pass = num_pass + 1;
    end else begin
      $display("[FAIL] Test %0d: test_tvalid_behavior -- o_tvalid unexpectedly went high", test_num);
      num_fail = num_fail + 1;
      log_fail("test_tvalid_behavior", "o_tvalid went high even though the assert lines are commented out");
    end
  end
  endtask

  // =======================================================
  //  TEST: reset mid-word
  //  Assert rst_n partway through a word and check everything
  //  clears cleanly instead of latching a stale value.
  // =======================================================
  task test_reset_mid_word;
  begin
    test_num = test_num + 1;

    fork
      i2s_drive_bits(1'b0, 24'h555555);
      begin
        repeat (10) @(posedge clk);   // interrupt after 10 of 24 bits
        rst_n = 1'b0;
      end
    join

    #(CLK_PERIOD * 3);
    @(posedge clk);
    rst_n = 1'b1;
    @(posedge clk);

    if (tdata === {WIDTH{1'b0}} && o_tvalid === 1'b0 &&
        dut.channel_1 === {WIDTH{1'b0}} && dut.channel_2 === {WIDTH{1'b0}} &&
        dut.word_counter === {COUNTER_BITS{1'b0}} && dut.state === 1'b0) begin
      $display("[PASS] Test %0d: test_reset_mid_word", test_num);
      num_pass = num_pass + 1;
    end else begin
      $display("[FAIL] Test %0d: test_reset_mid_word", test_num);
      $display("        tdata=%h o_tvalid=%b channel_1=%h channel_2=%h word_counter=%0d state=%b",
                tdata, o_tvalid, dut.channel_1, dut.channel_2, dut.word_counter, dut.state);
      num_fail = num_fail + 1;
      log_fail("test_reset_mid_word", "internal state not fully cleared by a reset asserted mid-word");
    end
  end
  endtask

  // ======================= Timeout =======================
  initial begin
    #20000;  // 20us max simulation time
    $display("\n[TIMEOUT] Simulation did not finish in time - forcing summary.");
    print_summary;
    $finish;
  end

  // ======================= Waveform dump =======================
  initial begin
    $dumpfile("i2s_in_tb.vcd");
    $dumpvars(0, i2s_in_tb);
  end

endmodule

sim/i2s_transceiver_in/i2s_in_tb.vcd
$date
	Tue Jun 30 17:22:10 2026
$end
$version
	Icarus Verilog
$end
$timescale
	1ps
$end
$scope module i2s_in_tb $end
$var wire 24 ! tdata [23:0] $end
$var wire 1 " o_tvalid $end
$var parameter 32 # CLK_PERIOD $end
$var parameter 32 $ COUNTER_BITS $end
$var parameter 32 % WIDTH $end
$var reg 1 & clk $end
$var reg 1 ' found_ch1 $end
$var reg 1 ( found_ch2 $end
$var reg 1 ) found_d $end
$var reg 1 * o_tready $end
$var reg 1 + rst_n $end
$var reg 1 , sd $end
$var reg 1 - tvalid_seen_high $end
$var reg 24 . word_c [23:0] $end
$var reg 24 / word_ch1 [23:0] $end
$var reg 24 0 word_ch2 [23:0] $end
$var reg 24 1 word_d [23:0] $end
$var reg 24 2 word_tv [23:0] $end
$var reg 1 3 ws $end
$var integer 32 4 fail_count [31:0] $end
$var integer 32 5 num_fail [31:0] $end
$var integer 32 6 num_pass [31:0] $end
$var integer 32 7 test_num [31:0] $end
$var integer 32 8 tv_i [31:0] $end
$scope module dut $end
$var wire 1 & clk $end
$var wire 1 * o_tready $end
$var wire 1 + rst_n $end
$var wire 1 , sd $end
$var wire 1 3 ws $end
$var parameter 32 9 COUNTER_BITS $end
$var parameter 32 : WIDTH $end
$var reg 24 ; channel_1 [23:0] $end
$var reg 24 < channel_2 [23:0] $end
$var reg 1 " o_tvalid $end
$var reg 1 = r_sd $end
$var reg 1 > r_ws $end
$var reg 1 ? r_ws_last $end
$var reg 1 @ state $end
$var reg 24 A tdata [23:0] $end
$var reg 5 B word_counter [4:0] $end
$upscope $end
$scope task i2s_drive_bits $end
$var reg 24 C data [23:0] $end
$var reg 1 D ws_val $end
$var integer 32 E bit_i [31:0] $end
$upscope $end
$scope task log_fail $end
$var reg 640 F detail [639:0] $end
$var reg 384 G name [383:0] $end
$upscope $end
$scope task print_summary $end
$var integer 32 H f [31:0] $end
$upscope $end
$scope task reset $end
$upscope $end
$scope task test_back_to_back_words $end
$upscope $end
$scope task test_reset_mid_word $end
$upscope $end
$scope task test_reset_state $end
$upscope $end
$scope task test_single_word_ch1 $end
$upscope $end
$scope task test_single_word_ch2 $end
$upscope $end
$scope task test_tvalid_behavior $end
$upscope $end
$scope task wait_for_tdata $end
$var reg 24 I expected [23:0] $end
$var reg 1 J found $end
$var integer 32 K k [31:0] $end
$var integer 32 L timeout_cycles [31:0] $end
$upscope $end
$upscope $end
$enddefinitions $end
$comment Show the parameter values. $end
$dumpall
b11000 :
b101 9
b11000 %
b101 $
b1010 #
$end
#0
$dumpvars
bx L
bx K
xJ
bx I
bx H
bx G
bx F
bx E
xD
bx C
bx B
bx A
x@
x?
x>
x=
bx <
bx ;
bx 8
b0 7
b0 6
b0 5
b0 4
13
bx 2
bx 1
bx 0
bx /
bx .
x-
0,
0+
1*
x)
x(
x'
0&
x"
bx !
$end
#5000
0@
b0 <
b0 ;
b0 B
1?
1>
0=
b0 !
b0 A
0"
1&
#10000
0&
#15000
1&
#20000
0&
#25000
1&
#30000
0&
#35000
1+
1&
#40000
0&
#45000
0+
b1 6
b1 7
1&
#50000
0&
#55000
1&
#60000
0&
#65000
1&
#70000
0&
#75000
1+
1&
#80000
0&
#85000
b0 E
b101001011100001100111100 C
0D
b101001011100001100111100 /
b10 7
1&
#90000
1,
03
0&
#95000
1=
0>
b1 E
1&
#100000
0,
0&
#105000
b100000000000000000000000 ;
1@
b1 B
0?
0=
b10 E
1&
#110000
1,
0&
#115000
b10 B
1=
b11 E
1&
#120000
0,
0&
#125000
b11 B
b101000000000000000000000 ;
0=
b100 E
1&
#130000
0&
#135000
b100 B
b101 E
1&
#140000
1,
0&
#145000
b101 B
1=
b110 E
1&
#150000
0,
0&
#155000
b110 B
b101001000000000000000000 ;
0=
b111 E
1&
#160000
1,
0&
#165000
b111 B
1=
b1000 E
1&
#170000
0&
#175000
b1000 B
b101001010000000000000000 ;
b1001 E
1&
#180000
0&
#185000
b1001 B
b101001011000000000000000 ;
b1010 E
1&
#190000
0,
0&
#195000
b1010 B
b101001011100000000000000 ;
0=
b1011 E
1&
#200000
0&
#205000
b1011 B
b1100 E
1&
#210000
0&
#215000
b1100 B
b1101 E
1&
#220000
0&
#225000
b1101 B
b1110 E
1&
#230000
1,
0&
#235000
b1110 B
1=
b1111 E
1&
#240000
0&
#245000
b1111 B
b101001011100001000000000 ;
b10000 E
1&
#250000
0,
0&
#255000
b10000 B
b101001011100001100000000 ;
0=
b10001 E
1&
#260000
0&
#265000
b10001 B
b10010 E
1&
#270000
1,
0&
#275000
b10010 B
1=
b10011 E
1&
#280000
0&
#285000
b10011 B
b101001011100001100100000 ;
b10100 E
1&
#290000
0&
#295000
b10100 B
b101001011100001100110000 ;
b10101 E
1&
#300000
0&
#305000
b10101 B
b101001011100001100111000 ;
b10110 E
1&
#310000
0,
0&
#315000
b10110 B
b101001011100001100111100 ;
0=
b10111 E
1&
#320000
0&
#325000
b10111 B
b0 K
0J
b1010 L
b101001011100001100111100 I
b11000 E
1&
#330000
0&
#335000
b11000 B
b1 K
1&
#340000
0&
#345000
b101001011100001100111100 !
b101001011100001100111100 A
0@
b10 K
1&
#350000
0&
#355000
b11 K
1J
1&
#360000
0&
#365000
b100 K
1&
#370000
0&
#375000
b101 K
1&
#380000
0&
#385000
b110 K
1&
#390000
0&
#395000
b111 K
1&
#400000
0&
#405000
b1000 K
1&
#410000
0&
#415000
b1001 K
1&
#420000
0&
#425000
b0 E
b11111100001001000110100 C
1D
b11111100001001000110100 0
b11 7
b10 6
1'
b1010 K
1&
#430000
13
0&
#435000
1>
b1 E
1&
#440000
1,
0&
#445000
1@
b1 B
1?
1=
b10 E
1&
#450000
0&
#455000
b10 B
b10000000000000000000000 <
b11 E
1&
#460000
0&
#465000
b11 B
b11000000000000000000000 <
b100 E
1&
#470000
0&
#475000
b100 B
b11100000000000000000000 <
b101 E
1&
#480000
0&
#485000
b101 B
b11110000000000000000000 <
b110 E
1&
#490000
0&
#495000
b110 B
b11111000000000000000000 <
b111 E
1&
#500000
0,
0&
#505000
b111 B
b11111100000000000000000 <
0=
b1000 E
1&
#510000
0&
#515000
b1000 B
b1001 E
1&
#520000
0&
#525000
b1001 B
b1010 E
1&
#530000
0&
#535000
b1010 B
b1011 E
1&
#540000
1,
0&
#545000
b1011 B
1=
b1100 E
1&
#550000
0,
0&
#555000
b1100 B
b11111100001000000000000 <
0=
b1101 E
1&
#560000
0&
#565000
b1101 B
b1110 E
1&
#570000
1,
0&
#575000
b1110 B
1=
b1111 E
1&
#580000
0,
0&
#585000
b1111 B
b11111100001001000000000 <
0=
b10000 E
1&
#590000
0&
#595000
b10000 B
b10001 E
1&
#600000
0&
#605000
b10001 B
b10010 E
1&
#610000
1,
0&
#615000
b10010 B
1=
b10011 E
1&
#620000
0&
#625000
b10011 B
b11111100001001000100000 <
b10100 E
1&
#630000
0,
0&
#635000
b10100 B
b11111100001001000110000 <
0=
b10101 E
1&
#640000
1,
0&
#645000
b10101 B
1=
b10110 E
1&
#650000
0,
0&
#655000
b10110 B
b11111100001001000110100 <
0=
b10111 E
1&
#660000
0&
#665000
b10111 B
b0 K
0J
b11111100001001000110100 I
b11000 E
1&
#670000
0&
#675000
b11000 B
b1 K
1&
#680000
0&
#685000
b11111100001001000110100 !
b11111100001001000110100 A
0@
b10 K
1&
#690000
0&
#695000
b11 K
1J
1&
#700000
0&
#705000
b100 K
1&
#710000
0&
#715000
b101 K
1&
#720000
0&
#725000
b110 K
1&
#730000
0&
#735000
b111 K
1&
#740000
0&
#745000
b1000 K
1&
#750000
0&
#755000
b1001 K
1&
#760000
0&
#765000
b0 E
b100010010001000110011 C
0D
b111111101101110010111010 1
b100010010001000110011 .
b11 6
1(
b1010 K
1&
#770000
03
0&
#775000
0>
b1 E
1&
#780000
0&
#785000
b1001011100001100111100 ;
1@
b1 B
0?
b10 E
1&
#790000
0&
#795000
b10 B
b11 E
1&
#800000
1,
0&
#805000
b11 B
b1011100001100111100 ;
1=
b100 E
1&
#810000
0,
0&
#815000
b100 B
b101011100001100111100 ;
0=
b101 E
1&
#820000
0&
#825000
b101 B
b110 E
1&
#830000
0&
#835000
b110 B
b100011100001100111100 ;
b111 E
1&
#840000
1,
0&
#845000
b111 B
1=
b1000 E
1&
#850000
0,
0&
#855000
b1000 B
0=
b1001 E
1&
#860000
0&
#865000
b1001 B
b100010100001100111100 ;
b1010 E
1&
#870000
1,
0&
#875000
b1010 B
b100010000001100111100 ;
1=
b1011 E
1&
#880000
0,
0&
#885000
b1011 B
b100010010001100111100 ;
0=
b1100 E
1&
#890000
0&
#895000
b1100 B
b1101 E
1&
#900000
0&
#905000
b1101 B
b1110 E
1&
#910000
1,
0&
#915000
b1110 B
1=
b1111 E
1&
#920000
0,
0&
#925000
b1111 B
0=
b10000 E
1&
#930000
0&
#935000
b10000 B
b100010010001000111100 ;
b10001 E
1&
#940000
0&
#945000
b10001 B
b10010 E
1&
#950000
1,
0&
#955000
b10010 B
1=
b10011 E
1&
#960000
0&
#965000
b10011 B
b10100 E
1&
#970000
0,
0&
#975000
b10100 B
0=
b10101 E
1&
#980000
0&
#985000
b10101 B
b100010010001000110100 ;
b10110 E
1&
#990000
1,
0&
#995000
b10110 B
b100010010001000110000 ;
1=
b10111 E
1&
#1000000
0&
#1005000
b10111 B
b100010010001000110010 ;
b111111101101110010111010 C
1D
b0 E
1&
#1010000
13
0&
#1015000
b11000 B
b100010010001000110011 ;
1>
b1 E
1&
#1020000
0&
#1025000
b111111100001001000110100 <
b1 B
1?
b10 E
1&
#1030000
0&
#1035000
b10 B
b11 E
1&
#1040000
0&
#1045000
b11 B
b100 E
1&
#1050000
0&
#1055000
b100 B
b101 E
1&
#1060000
0&
#1065000
b101 B
b110 E
1&
#1070000
0&
#1075000
b110 B
b111 E
1&
#1080000
0,
0&
#1085000
b111 B
0=
b1000 E
1&
#1090000
1,
0&
#1095000
b1000 B
1=
b1001 E
1&
#1100000
0&
#1105000
b1001 B
b111111101001001000110100 <
b1010 E
1&
#1110000
0,
0&
#1115000
b1010 B
b111111101101001000110100 <
0=
b1011 E
1&
#1120000
1,
0&
#1125000
b1011 B
1=
b1100 E
1&
#1130000
0&
#1135000
b1100 B
b1101 E
1&
#1140000
0&
#1145000
b1101 B
b111111101101101000110100 <
b1110 E
1&
#1150000
0,
0&
#1155000
b1110 B
b111111101101111000110100 <
0=
b1111 E
1&
#1160000
0&
#1165000
b1111 B
b111111101101110000110100 <
b10000 E
1&
#1170000
1,
0&
#1175000
b10000 B
1=
b10001 E
1&
#1180000
0,
0&
#1185000
b10001 B
b111111101101110010110100 <
0=
b10010 E
1&
#1190000
1,
0&
#1195000
b10010 B
1=
b10011 E
1&
#1200000
0&
#1205000
b10011 B
b10100 E
1&
#1210000
0&
#1215000
b10100 B
b10101 E
1&
#1220000
0,
0&
#1225000
b10101 B
b111111101101110010111100 <
0=
b10110 E
1&
#1230000
1,
0&
#1235000
b10110 B
b111111101101110010111000 <
1=
b10111 E
1&
#1240000
0,
0&
#1245000
b10111 B
b111111101101110010111010 <
0=
b0 K
0J
b111111101101110010111010 I
b100 6
b100 7
b11000 E
1&
#1250000
0&
#1255000
b11000 B
b1 K
1&
#1260000
0&
#1265000
b111111101101110010111010 !
b111111101101110010111010 A
0@
b10 K
1&
#1270000
0&
#1275000
b11 K
1J
1&
#1280000
0&
#1285000
b100 K
1&
#1290000
0&
#1295000
b101 K
1&
#1300000
0&
#1305000
b110 K
1&
#1310000
0&
#1315000
b111 K
1&
#1320000
0&
#1325000
b1000 K
1&
#1330000
0&
#1335000
b1001 K
1&
#1340000
0&
#1345000
0+
b101 6
b101 7
1)
b1010 K
1&
#1350000
0&
#1355000
b0 <
b0 ;
b0 B
b0 !
b0 A
1&
#1360000
0&
#1365000
1&
#1370000
0&
#1375000
1+
1&
#1380000
0&
#1385000
b0 8
0-
b1111111100000000 2
b110 7
1&
#1390000
03
0&
#1395000
0>
b1 8
1&
#1400000
0&
#1405000
1@
b1 B
0?
b10 8
1&
#1410000
0&
#1415000
b10 B
b11 8
1&
#1420000
0&
#1425000
b11 B
b100 8
1&
#1430000
0&
#1435000
b100 B
b101 8
1&
#1440000
0&
#1445000
b101 B
b110 8
1&
#1450000
0&
#1455000
b110 B
b111 8
1&
#1460000
0&
#1465000
b111 B
b1000 8
1&
#1470000
1,
0&
#1475000
b1000 B
1=
b1001 8
1&
#1480000
0&
#1485000
b1001 B
b1000000000000000 ;
b1010 8
1&
#1490000
0&
#1495000
b1010 B
b1100000000000000 ;
b1011 8
1&
#1500000
0&
#1505000
b1011 B
b1110000000000000 ;
b1100 8
1&
#1510000
0&
#1515000
b1100 B
b1111000000000000 ;
b1101 8
1&
#1520000
0&
#1525000
b1101 B
b1111100000000000 ;
b1110 8
1&
#1530000
0&
#1535000
b1110 B
b1111110000000000 ;
b1111 8
1&
#1540000
0&
#1545000
b1111 B
b1111111000000000 ;
b10000 8
1&
#1550000
0,
0&
#1555000
b10000 B
b1111111100000000 ;
0=
b10001 8
1&
#1560000
0&
#1565000
b10001 B
b10010 8
1&
#1570000
0&
#1575000
b10010 B
b10011 8
1&
#1580000
0&
#1585000
b10011 B
b10100 8
1&
#1590000
0&
#1595000
b10100 B
b10101 8
1&
#1600000
0&
#1605000
b10101 B
b10110 8
1&
#1610000
0&
#1615000
b10110 B
b10111 8
1&
#1620000
0&
#1625000
b10111 B
b0 E
b10101010101010101010101 C
0D
b111 7
b110 6
b11000 8
1&
#1630000
0&
#1635000
b11000 B
b1 E
1&
#1640000
1,
0&
#1645000
b1111111100000000 !
b1111111100000000 A
0@
1=
b10 E
1&
#1650000
0,
0&
#1655000
0=
b11 E
1&
#1660000
1,
0&
#1665000
1=
b100 E
1&
#1670000
0,
0&
#1675000
0=
b101 E
1&
#1680000
1,
0&
#1685000
1=
b110 E
1&
#1690000
0,
0&
#1695000
0=
b111 E
1&
#1700000
1,
0&
#1705000
1=
b1000 E
1&
#1710000
0,
0&
#1715000
0=
b1001 E
1&
#1720000
1,
0&
#1725000
1=
0+
b1010 E
1&
#1730000
0,
0&
#1735000
b0 ;
b0 B
0=
b0 !
b0 A
b1011 E
1&
#1740000
1,
0&
#1745000
b1100 E
1&
#1750000
0,
0&
#1755000
b1101 E
1&
#1760000
1,
0&
#1765000
b1110 E
1&
#1770000
0,
0&
#1775000
b1111 E
1&
#1780000
1,
0&
#1785000
b10000 E
1&
#1790000
0,
0&
#1795000
b10001 E
1&
#1800000
1,
0&
#1805000
b10010 E
1&
#1810000
0,
0&
#1815000
b10011 E
1&
#1820000
1,
0&
#1825000
b10100 E
1&
#1830000
0,
0&
#1835000
b10101 E
1&
#1840000
1,
0&
#1845000
b10110 E
1&
#1850000
0,
0&
#1855000
b10111 E
1&
#1860000
1,
0&
#1865000
b11000 E
1&
#1870000
0&
#1875000
1&
#1880000
0&
#1885000
1&
#1890000
0&
#1895000
1=
1+
1&
#1900000
0&
#1905000
b111 6
1&
